baseconnect/__init__.py
baseconnect/database.py
baseconnect-1.1.dist-info/METADATA
baseconnect-1.1.dist-info/WHEEL
baseconnect-1.1.dist-info/top_level.txt
baseconnect-1.1.dist-info/RECORD
