Metadata-Version: 2.1
Name: baseconnect
Version: 1.1
Summary: Database connection library for SQL Server
Home-page: https://github.com/Domiterd/BaseConnect
Author: Domiter Dominik
Author-email: dominik.domiter@autowallis.hu
Requires-Dist: pyodbc
Requires-Dist: pandas
